MANIFEST.in
README
release-checklist.txt
setup.py
doc/Makefile
doc/changes.rst
doc/cholmod.rst
doc/conf.py
doc/index.rst
doc/make.bat
doc/overview.rst
scikits/__init__.py
scikits.sparse.egg-info/PKG-INFO
scikits.sparse.egg-info/SOURCES.txt
scikits.sparse.egg-info/dependency_links.txt
scikits.sparse.egg-info/namespace_packages.txt
scikits.sparse.egg-info/not-zip-safe
scikits.sparse.egg-info/requires.txt
scikits.sparse.egg-info/top_level.txt
scikits/sparse/__init__.py
scikits/sparse/cholmod.pyx
scikits/sparse/test_cholmod.py
scikits/sparse/test_data/illc1033.mtx.gz
scikits/sparse/test_data/illc1033_rhs1.mtx.gz
scikits/sparse/test_data/illc1850.mtx.gz
scikits/sparse/test_data/illc1850_rhs1.mtx.gz
scikits/sparse/test_data/well1033.mtx.gz
scikits/sparse/test_data/well1033_rhs1.mtx.gz
scikits/sparse/test_data/well1850.mtx.gz
scikits/sparse/test_data/well1850_rhs1.mtx.gz