Metadata-Version: 1.1
Name: scikits.sparse
Version: 0.2
Summary: Scikits sparse matrix package
Home-page: https://github.com/njsmith/scikits-sparse/
Author: ('Nathaniel Smith',)
Author-email: ('njs@pobox.com',)
License: GPL
Download-URL: https://github.com/njsmith/scikits-sparse/downloads
Platform: UNKNOWN
Classifier: Development Status :: 3 - Alpha
Classifier: Environment :: Console
Classifier: Intended Audience :: Developers
Classifier: Intended Audience :: Science/Research
Classifier: License :: OSI Approved :: GNU General Public License (GPL)
Classifier: Topic :: Scientific/Engineering
